geoffrey_filecontent-0.0.4.dist-info/DESCRIPTION.rst
geoffrey_filecontent-0.0.4.dist-info/RECORD
geoffrey_filecontent-0.0.4.dist-info/WHEEL
geoffrey_filecontent-0.0.4.dist-info/top_level.txt
geoffrey_filecontent-0.0.4.dist-info/metadata.json
geoffrey_filecontent-0.0.4.dist-info/METADATA
geoffreyplugins/__init__.py
geoffreyplugins/filecontent.py
geoffreyplugins/filecontent/main.js
geoffreyplugins/filecontent/assets/panel.html
geoffreyplugins/filecontent/assets/.gitkeep
