Metadata-Version: 2.0
Name: geoffrey-filecontent
Version: 0.0.4
Summary: Centralize multiple data source plugins.
Home-page: https://github.com/GeoffreyCI/geoffrey-filecontent
Author: Roberto Abdelkader Martínez Pérez
Author-email: robertomartinezp@gmail.com
License: UNKNOWN
Platform: UNKNOWN
Requires-Dist: filemagic (==1.6)
